allium/__init__.py
allium/sphere.py
allium-0.0.1.data/scripts/allium-echelle
allium-0.0.1.dist-info/LICENSE
allium-0.0.1.dist-info/METADATA
allium-0.0.1.dist-info/WHEEL
allium-0.0.1.dist-info/top_level.txt
allium-0.0.1.dist-info/RECORD
