Metadata-Version: 2.1
Name: allium
Version: 0.0.1
Summary: Compute oscillations of radially symmetric things
Home-page: https://gitlab.com/warrickball/aims3
Author: Warrick Ball
Author-email: W.H.Ball@bham.ac.uk
License: UNKNOWN
Platform: UNKNOWN
Classifier: Programming Language :: Python :: 3
Classifier: License :: OSI Approved :: MIT License
Classifier: Operating System :: OS Independent
Requires-Python: >=3.4
Requires-Dist: numpy
Requires-Dist: scipy
